[{"str":"john achieved the feat of couch potato","time":1350757058,"names":["john"]},{"str":"jtab purchased a new pet gimp called Erik_Revolution.","time":1350723728,"names":["jtab"]},{"str":"Erik_Revolution had a private dance with Zelly in a dark corner of public.tv.","time":1350704554,"names":["Erik_Revolution"]},{"str":"Erik_Revolution purchased a new pet gimp called Zelly.","time":1350704544,"names":["Erik_Revolution"]},{"str":"john achieved the feat of bob saget","time":1350704132,"names":["john"]},{"str":"john achieved the feat of copy cat","time":1350692373,"names":["john"]},{"str":"ryno10sman punched ryno10sman.","time":1350691833,"names":["ryno10sman"]},{"str":"john achieved the feat of ass wiper","time":1350691335,"names":["john"]},{"str":"john achieved the feat of triad dealer","time":1350690534,"names":["john"]},{"str":"john achieved the feat of risk taker","time":1350690534,"names":["john"]},{"str":"john achieved the feat of card sorter","time":1350690399,"names":["john"]},{"str":"xDiablox falcon punched rock and rockgvmt into the middle of next week.","time":1350681605,"names":["xDiablox"]},{"str":"Erik_Revolution recouped cock_pancake for the sum of 1306 cookies.","time":1350679671,"names":["Erik_Revolution"]},{"str":"kite recouped coal_bear for the sum of 1528 cookies.","time":1350673337,"names":["kite"]},{"str":"R_E_M_Y achieved the feat of video spammer","time":1350612822,"names":["R_E_M_Y"]},{"str":"R_E_M_Y achieved the feat of video nerd","time":1350612822,"names":["R_E_M_Y"]},{"str":"ryno10sman recouped industrialbunni for the sum of 12001 cookies.","time":1350608022,"names":["ryno10sman"]},{"str":"TakumiKun achieved the feat of super video star","time":1350553390,"names":["TakumiKun"]},{"str":"traces sniffed out 751242 belonging to kite.","time":1350537022,"names":["traces"]},{"str":"IndustrialBunni sniffed out 751248 belonging to kite.","time":1350530503,"names":["IndustrialBunni"]},{"str":"sk8t3r_B0Y recouped cwap for the sum of 10406 cookies.","time":1350521672,"names":["sk8t3r_B0Y"]},{"str":"Cloud9 achieved the feat of midget hater","time":1350507903,"names":["Cloud9"]},{"str":"Cloud9 achieved the feat of super n00b bonker","time":1350507798,"names":["Cloud9"]},{"str":"Cloud9 achieved the feat of dont come a knockin","time":1350506056,"names":["Cloud9"]},{"str":"Cloud9 achieved the feat of extreme bonker","time":1350506053,"names":["Cloud9"]},{"str":"Doom achieved the feat of couch new potato","time":1350458523,"names":["Doom"]},{"str":"Billy_Bob_Bean achieved the feat of couch sprout","time":1350453220,"names":["Billy_Bob_Bean"]},{"str":"Cloud9 achieved the feat of power bonker","time":1350446599,"names":["Cloud9"]},{"str":"Erik_Revolution purchased a new pet gimp called jtab.","time":1350440737,"names":["Erik_Revolution"]},{"str":"kite sniffed out 123995 belonging to Erik_Revolution.","time":1350440639,"names":["kite"]},{"str":"ryno10sman punched ryno10sman.","time":1350435033,"names":["ryno10sman"]},{"str":"Erik_Revolution recouped traces for the sum of 9986 cookies.","time":1350411751,"names":["Erik_Revolution"]},{"str":"jtab hugged kite and got away with 72961 cookies.","time":1350410793,"names":["jtab"]},{"str":"Aura recouped sixth for the sum of 17278 cookies.","time":1350409262,"names":["Aura"]},{"str":"kite farted in public.","time":1350347254,"names":["kite"]},{"str":"prison_born achieved the feat of super video star","time":1350323417,"names":["prison_born"]},{"str":"sovereign achieved the feat of video surfer","time":1350322716,"names":["sovereign"]},{"str":"KAM recouped hobbes for the sum of 11163 cookies.","time":1350311071,"names":["KAM"]},{"str":"TakumiKun achieved the feat of poseur","time":1350306635,"names":["TakumiKun"]},{"str":"Cloud9 achieved the feat of card collector","time":1350300362,"names":["Cloud9"]},{"str":"jtab recouped verms for the sum of 100119 cookies.","time":1350300293,"names":["jtab"]},{"str":"Cloud9 achieved the feat of byob bonker","time":1350296630,"names":["Cloud9"]},{"str":"Cloud9 achieved the feat of couch new potato","time":1350285288,"names":["Cloud9"]},{"str":"Cloud9 achieved the feat of video extender","time":1350281708,"names":["Cloud9"]},{"str":"Cloud9 achieved the feat of bob saget","time":1350270408,"names":["Cloud9"]},{"str":"Cloud9 achieved the feat of copy cat","time":1350270205,"names":["Cloud9"]},{"str":"Cloud9 achieved the feat of card sorter","time":1350270103,"names":["Cloud9"]},{"str":"Cloud9 achieved the feat of risk taker","time":1350266040,"names":["Cloud9"]},{"str":"Cloud9 achieved the feat of snappy dresser","time":1350265724,"names":["Cloud9"]},{"str":"kite recouped traces for the sum of 11821 cookies.","time":1349311912,"names":["kite"]}]